Workbook

Sheet 01 Cover
A2: FOLDABLE ELECTRIC SCOOTER CHARGING DOCK FOR APARTMENTS
A3: Financial Management Project | Start-up Business Plan
B5: Company Name | E5: ScootCharge Solutions Pvt. Ltd.
B6: Sector | E6: Clean-Tech / Urban Mobility Infrastructure
B7: Stage | E7: Pre-Revenue Start-up (Year 0 → Year 5)
B8: Base Currency | E8: Indian Rupees (₹) – amounts in ₹ Lakhs unless stated
B9: Prepared By | E9: Nandini Modgil, Devansh Gerg, Paridhi Somani, Vaidehi Patil, Atharva Sinnarkar, Adarshdeep Gupta
A11: WORKBOOK NAVIGATION
B12: Sheet Name | C12: Contents
B13: 01 Cover | C13: Introduction, company overview, document index
B14: 02 Industry | C14: Industry & sectoral analysis, market need, TAM/SAM/SOM
B15: 03 Competitor | C15: Competitor benchmarking, SWOT matrix
B16: 04 Assumptions | C16: All input assumptions (blue cells) – master control sheet
B17: 05 CapEx | C17: Capital requirements – short-term & long-term
B18: 06 Financing | C18: Sources of finance, capital structure, WACC
B19: 07 P&L | C19: 5-Year projected Income Statement
B20: 08 Balance Sheet | C20: 5-Year projected Balance Sheet
B21: 09 Cash Flow | C21: 5-Year projected Cash Flow Statement
B22: 10 Cap Budget | C22: NPV, IRR, Payback, Sensitivity analysis
B23: 11 Conclusion | C23: Summary KPIs, investment highlights

Sheet 02 Industry
A1: INDUSTRY & SECTORAL ANALYSIS
A3: 2.1 PROBLEM STATEMENT & MARKET NEED
A4: • Electric scooter ownership in urban India is growing at ~28% CAGR (2023-2028), yet 80% of apartments lack dedicated EV charging infrastructure.
A5: • Apartment residents rely on long extension cords, common area sockets, or public stations — all unsafe, inconvenient, and theft-prone.
A6: • Government FAME-II policy mandates EV-ready buildings, creating a regulatory tailwind for residential charging solutions.
A7: • ScootCharge addresses this gap: a foldable, lockable, smart charging dock designed specifically for apartment balconies and parking bays.
A9: 2.2 MARKET SIZING (₹ Crores)
A10: Segment | B10: Definition | C10: FY 2024 | D10: FY 2026E | E10: FY 2028E | F10: CAGR | G10: Basis
A11: TAM – Total Addressable Market | B11: All EV 2-wheeler owners in India needing home charging | C11: ₹ 4,200 | D11: ₹ 6,800 | E11: ₹ 11,200 | F11: 26% | G11: SMEV + NITI Aayog estimates
A12: SAM – Serviceable Addressable Market | B12: Apartment-dwelling EV 2-wheeler owners in Tier-1 cities | C12: ₹ 840 | D12: ₹ 1,560 | E12: ₹ 2,900 | F12: 28% | G12: Urban housing census data
A13: SOM – Serviceable Obtainable Market | B13: ScootCharge realistic capture (3-5% SAM) | C13: ₹ 25 | D13: ₹ 62 | E13: ₹ 145 | F13: 35% | G13: Bottom-up sales model
A15: 2.3 KEY INDUSTRY TRENDS
A16: Regulatory | B16: FAME-II subsidy ₹10,000 Cr; building codes mandating EV parking in new residential projects
A17: Technology | B17: IoT-enabled smart docks with mobile app, energy monitoring, OTA updates
A18: Consumer | B18: Rising fuel costs (+22% since 2022) accelerating EV adoption among urban millennials
A19: Competitive | B19: No dominant player in apartment-specific foldable dock segment — white-space opportunity
A20: Financial | B20: VC funding in EV infrastructure up 3× YoY; SIDBI and NABARD green-finance schemes available

Sheet 03 Competitor
A1: COMPETITOR ANALYSIS
A3: 3.1 COMPETITIVE LANDSCAPE
A4: Company / Product | B4: Segment | C4: Price (₹) | D4: Smart App | E4: Foldable | F4: Apt-Specific | G4: Strength | H4: Weakness
A5: ScootCharge Dock (Our Product) | B5: Apartment Foldable | C5: 3,499–4,999 | D5: Yes | E5: Yes | F5: Yes | G5: Only apt-specific foldable; IoT; compact | H5: New brand; limited distribution
A6: Ather Grid | B6: Public Station | C6: N/A (sub) | D6: Yes | E6: No | F6: No | G6: Strong brand; Ather ecosystem | H6: Not home/apartment focused
A7: Lectrix Charge | B7: Home Wall Charger | C7: 5,999–8,999 | D7: Yes | E7: No | F7: No | G7: Established brand; reliable hardware | H7: Bulky; needs dedicated wall space
A8: AmpereVolt HomeCharge | B8: Home Wall Charger | C8: 4,500–6,500 | D8: Limited | E8: No | F8: No | G8: Lower price point | H8: No app; no foldable option
A9: Generic Chinese OEM Docks | B9: Generic | C9: 1,200–2,500 | D9: No | E9: Some | F9: No | G9: Very low price | H9: No safety cert; no warranty; unreliable
A10: Tata Power EZ Home | B10: Home Wall AC | C10: 7,000–12,000 | D10: Yes | E10: No | F10: No | G10: Tata brand trust; national service | H10: Premium pricing; apartment unfriendly
A12: 3.2 COMPETITIVE SCORING MATRIX (1 = Low, 5 = High)
A13: Criteria | B13: Weight | C13: ScootCharge | D13: Ather Grid | E13: Lectrix | F13: AmpereVolt | G13: Chinese OEM | H13: Tata Power EZ
A14: Price Value | B14: 0.2 | C14: 4 | D14: 5 | E14: 5 | F14: 4 | G14: 5 | H14: 2 | I14: 3
A15: Smart Features | B15: 0.2 | C15: 3 | D15: 5 | E15: 2 | F15: 5 | G15: 2 | H15: 5 | I15: 4
A16: Portability | B16: 0.15 | C16: 3 | D16: 4 | E16: 2 | F16: 4 | G16: 3 | H16: 4 | I16: 4
A17: Safety Certs | B17: 0.15 | C17: 4 | D17: 2 | E17: 2 | F17: 3 | G17: 3 | H17: 3 | I17: 2
A18: Apt Suitability | B18: 0.15 | C18: 5 | D18: 1 | E18: 3 | F18: 1 | G18: 2 | H18: 1 | I18: 1
A19: Brand Trust | B19: 0.1 | C19: 2 | D19: 4 | E19: 2 | F19: 5 | G19: 2 | H19: 5 | I19: 4
A20: After-Sales | B20: 0.05
A21: WEIGHTED SCORE | B21: - | C21: =SUMPRODUCT(C14:C20,$B$14:$B$20) -> 3.4 | D21: =SUMPRODUCT(D14:D20,$B$14:$B$20) -> 3.45 | E21: =SUMPRODUCT(E14:E20,$B$14:$B$20) -> 2.65 | F21: =SUMPRODUCT(F14:F20,$B$14:$B$20) -> 3.5 | G21: =SUMPRODUCT(G14:G20,$B$14:$B$20) -> 2.8 | H21: =SUMPRODUCT(H14:H20,$B$14:$B$20) -> 3.1

Sheet 04 Assumptions
A1: MASTER ASSUMPTIONS SHEET (Blue = Input Cells)
A2: Change blue cells to run scenarios. All other sheets pull from here.
A4: A. PRODUCT & PRICING
A5: ASP – B2C Dock (₹) | B5: 3999 | C5: ₹ | D5: Average selling price per unit, B2C channel
A6: ASP – B2B Dock (₹) | B6: 3499 | C6: ₹ | D6: Bulk price to housing societies (10+ units)
A7: ASP – Smart Subscription (₹/yr) | B7: 799 | C7: ₹ | D7: Annual IoT app subscription per user
A8: COGS per unit – Material (₹) | B8: 1800 | C8: ₹ | D8: BOM: PCB, plastics, cable, packaging
A9: COGS per unit – Labour (₹) | B9: 220 | C9: ₹ | D9: Assembly + QC per unit
A10: COGS per unit – Logistics (₹) | B10: 180 | C10: ₹ | D10: Last-mile delivery cost per unit
A11: Warranty provision (% of revenue) | B11: 0.02 | C11: % | D11: Accrual for warranty claims
A13: B. SALES VOLUME (Units)
B14: FY1 | C14: FY2 | D14: FY3 | E14: FY4 | F14: FY5
A15: B2C Units Sold | B15: 500 | C15: 1200 | D15: 2500 | E15: 4200 | F15: 6800 | G15: Source: Bottom-up sales model + industry CAGR 28%
A16: B2B Units Sold | B16: 200 | C16: 600 | D16: 1400 | E16: 2600 | F16: 4200 | G16: Source: Bottom-up sales model + industry CAGR 28%
A17: Subscription Renewals | B17: 0 | C17: 500 | D17: 1400 | E17: 3200 | F17: 6400 | G17: Source: Bottom-up sales model + industry CAGR 28%
A18: B2C Price Growth (YoY %) | B18: 0 | C18: 0.03 | D18: 0.03 | E18: 0.05 | F18: 0.05 | G18: Source: Bottom-up sales model + industry CAGR 28%
A19: B2B Price Growth (YoY %) | B19: 0 | C19: 0.02 | D19: 0.02 | E19: 0.03 | F19: 0.03 | G19: Source: Bottom-up sales model + industry CAGR 28%
A21: C. OPERATING EXPENSES (₹ Lakhs / Year)
A22: Salaries & Benefits – Year 1 (₹L) | B22: 12 | C22: ₹L | G22: 4 founders + 3 staff
A23: Salaries Growth (% pa) | B23: 0.15 | C23: % | G23: Annual increment
A24: Marketing & Brand – Year 1 (₹L) | B24: 8 | C24: ₹L | G24: Digital + BTL + exhibitions
A25: Marketing Growth (% pa) | B25: 0.2 | C25: % | G25: Scales with revenue
A26: R&D / Product Dev – Year 1 (₹L) | B26: 5 | C26: ₹L | G26: Next-gen dock v2.0
A27: G&A Overheads – Year 1 (₹L) | B27: 4 | C27: ₹L | G27: Rent, utilities, insurance
A28: G&A Growth (% pa) | B28: 0.08 | C28: % | G28: Near-inflation escalation
A29: Depreciation – Plant (years) | B29: 5 | C29: Yrs | G29: SLM on plant & machinery
A30: Depreciation – Furniture/IT (years) | B30: 3 | C30: Yrs | G30: SLM
A31: Amortisation – Intangibles (years) | B31: 5 | C31: Yrs | G31: Patent + software
A33: D. TAX, DISCOUNT & MACRO
A34: Corporate Tax Rate | B34: 0.25 | C34: % | G34: India flat-rate Startup scheme
A35: GST Rate – Hardware | B35: 0.18 | C35: % | G35: EV chargers at 18% GST
A36: GST Rate – Subscription | B36: 0.18 | C36: % | G36: Software services
A37: Inflation / Cost Escalation | B37: 0.06 | C37: % | G37: RBI target band
A38: Risk-Free Rate (Rf) | B38: 0.073 | C38: % | G38: 10-yr Indian G-Sec yield
A39: Market Risk Premium (Rm-Rf) | B39: 0.065 | C39: % | G39: Damodaran India ERP
A40: Beta (Levered) | B40: 1.35 | C40: x | G40: Tech-hardware startup proxy
A41: Cost of Debt (pre-tax) | B41: 0.12 | C41: % | G41: SIDBI/bank term loan rate
A42: Terminal Growth Rate | B42: 0.04 | C42: % | G42: Conservative long-run growth

Sheet 05 CapEx
A1: CAPITAL REQUIREMENTS (₹ Lakhs)
A3: 5.1 SHORT-TERM CAPITAL REQUIREMENTS (Year 0 – Pre-launch)
A4: Item | B4: Category | C4: Qty | D4: Unit Cost (₹) | E4: Total (₹L) | F4: Useful Life | G4: Notes
A5: Product Design & CAD | B5: Intangible | C5: 1 | D5: 200000 | E5: 2 | F5: 5 yrs | G5: Industrial design + mould design
A6: Patent Filing (India + PCT) | B6: Intangible | C6: 1 | D6: 150000 | E6: 1.5 | F6: 10 yrs | G6: IP protection
A7: Prototype Development | B7: Intangible | C7: 5 | D7: 40000 | E7: 2 | F7: – | G7: 5 working prototypes
A8: PCB + Electronics tooling | B8: Plant | C8: 1 | D8: 300000 | E8: 3 | F8: 5 yrs | G8: Injection mould tooling
A9: Test & Certification (BIS/CE) | B9: Intangible | C9: 1 | D9: 250000 | E9: 2.5 | F9: 3 yrs | G9: Mandatory certifications
A10: ERP + Accounting Software | B10: Intangible | C10: 1 | D10: 120000 | E10: 1.2 | F10: 3 yrs | G10: Zoho Books + Inventory
A11: Website + App MVP | B11: Intangible | C11: 1 | D11: 180000 | E11: 1.8 | F11: 3 yrs | G11: IoT app + e-commerce site
A12: Office Setup (leasehold) | B12: Furniture | C12: 1 | D12: 200000 | E12: 2 | F12: 3 yrs | G12: Workstations, AC, fixtures
A13: Initial Inventory (500 units) | B13: Working Cap | C13: 500 | D13: 2200 | E13: 11 | F13: – | G13: COGS/unit × 500 buffer stock
A14: Working Capital Buffer | B14: Working Cap | C14: 1 | D14: 500000 | E14: 5 | F14: – | G14: 3 months operating expenses
A15: Pre-launch Marketing | B15: Revenue | C15: 1 | D15: 300000 | E15: 3 | F15: – | G15: Digital, exhibitions, PR
A16: Contingency (10%) | B16: Contingency | C16: 1 | D16: 0 | E16: =SUM(E5:E15)*0.1 -> 3.5 | F16: – | G16: 10% contingency on all items above
A17: TOTAL SHORT-TERM CAPEX | E17: =SUM(E5:E16) -> 38.5 | G17: Pre-launch + Y1 working capital
A20: 5.2 LONG-TERM CAPITAL REQUIREMENTS (Year 2–5 Expansion)
A21: Item | B21: Year | C21: ₹ Lakhs | D21: Purpose
A22: Assembly Line Upgrade (semi-auto) | B22: Year 2 | C22: 15 | D22: Scale to 5,000 units/yr capacity
A23: Warehouse Lease Deposit | B23: Year 2 | C23: 6 | D23: 5,000 sq ft Mumbai / Pune warehouse
A24: Fleet of Delivery Vehicles (2) | B24: Year 2 | C24: 8 | D24: B2B installation van
A25: Second-Gen Product Tooling | B25: Year 3 | C25: 10 | D25: Dock v2.0 – fast-charge + solar
A26: CRM & Business Analytics Suite | B26: Year 3 | C26: 3 | D26: Salesforce + Power BI
A27: Expansion to 5 cities – Marketing | B27: Year 3 | C27: 12 | D27: Bangalore, Hyderabad, Chennai, Pune, Delhi
A28: New Mould (3 SKU variants) | B28: Year 4 | C28: 8 | D28: Premium / Standard / Budget SKUs
A29: Export Market Setup (SEA) | B29: Year 4 | C29: 10 | D29: Singapore / Malaysia pilot
A30: Automated Assembly Plant | B30: Year 5 | C30: 35 | D30: 10,000+ units/yr; reduce COGS 15%
A31: Contingency (10%) | B31: – | C31: =SUM(C22:C30)*0.1 -> 10.7 | D31: 10% of above
A33: TOTAL LONG-TERM CAPEX | C33: =SUM(C22:C32) -> 117.7
A36: 5.3 TOTAL CAPITAL REQUIREMENT SUMMARY
A37: Short-Term CapEx (Pre-launch + Y1) | B37: =E17 -> 38.5
A38: Long-Term CapEx (Y2–Y5) | B38: =C33 -> 117.7
A39: GRAND TOTAL CAPITAL REQUIRED | B39: =C37+C38 -> 0

Sheet 06 Financing
A1: SOURCES OF FINANCE, CAPITAL STRUCTURE & COST OF CAPITAL
A3: 6.1 SOURCES OF FINANCE
A4: Source | B4: Type | C4: Amount (₹L) | D4: % of Total | E4: Interest/Return | F4: Tenure | G4: Notes
A5: Founder Equity | B5: Equity | C5: 18 | D5: =C5/C11 -> 0.32727273 | E5: N/A | F5: Perpetual | G5: 4 co-founders × ₹4.5L each
A6: Angel / Friends & Family Round | B6: Equity | C6: 12 | D6: =C6/C11 -> 0.21818182 | E6: ~30% IRR | F6: Y3–Y5 exit | G6: Convertible note option
A7: SIDBI CGTMSE Loan | B7: Debt | C7: 15 | D7: =C7/C11 -> 0.27272727 | E7: 11.5% | F7: 7 years | G7: Collateral-free for startups
A8: State Startup Grant (DPIIT) | B8: Grant | C8: 5 | D8: =C8/C11 -> 0.090909091 | E8: 0% | F8: One-time | G8: Non-refundable seed grant
A9: Bank OD / Working Capital Line | B9: Debt | C9: 5 | D9: =C9/C11 -> 0.090909091 | E9: 13.5% | F9: Revolving | G9: HDFC / SBI CC limit
A10: Retained Earnings (Y2 onward) | B10: Internal | C10: 0 | D10: =C10/C11 -> 0 | E10: – | F10: Ongoing | G10: Re-invested from Year 2 profits
A11: TOTAL FUNDING | C11: =SUM(C5:C10) -> 55
A14: 6.2 CAPITAL STRUCTURE & WACC CALCULATION
A15: Component | B15: Amount (₹L) | C15: Weight | D15: Cost (pre-tax) | E15: Tax Shield | F15: After-tax Cost | G15: Weighted Cost
A16: Equity (Founders + Angel) | B16: 30 | C16: =B16/B19 -> 0.54545455 | D16: ='04 Assumptions'!B34+'04 Assumptions'!B36*'04 Assumptions'!B35 -> 0.2824 | E16: N/A | F16: =D16 -> 0.2824 | G16: =C16*F16 -> 0.15403636
A17: Debt (SIDBI Loan + OD Line) | B17: 20 | C17: =B17/B19 -> 0.36363636 | D17: ='04 Assumptions'!B37 -> 0.06 | E17: ='04 Assumptions'!B33 -> 0 | F17: =D17*(1-E17) -> 0.06 | G17: =C17*F17 -> 0.021818182
A18: Grant (Non-repayable – treated as equity) | B18: 5 | C18: =B18/B19 -> 0.090909091 | D18: 0.0% | E18: N/A | F18: 0.0% | G18: 0.0%
A19: TOTAL / WACC | B19: =SUM(B16:B18) -> 55 | C19: 100.0% | F19: WACC ▶ | G19: =SUM(G16:G18) -> 0.17585455
A23: 6.3 LEVERAGE RATIOS
A24: Metric | B24: FY2026 (Y1) | C24: FY2027 (Y2) | D24: FY2028 (Y3) | E24: FY2029 (Y4) | F24: FY2030 (Y5) | G24: Benchmark
A25: CAPITAL MIX (₹ Lakhs)
A26: Total Debt | B26: ='08 Balance Sheet'!B22+'08 Balance Sheet'!B27 -> 20 | C26: ='08 Balance Sheet'!C22+'08 Balance Sheet'!C27 -> 17.9 | D26: ='08 Balance Sheet'!D22+'08 Balance Sheet'!D27 -> 15.8 | E26: ='08 Balance Sheet'!E22+'08 Balance Sheet'!E27 -> 10.5 | F26: ='08 Balance Sheet'!F22+'08 Balance Sheet'!F27 -> 4.5 | G26: –
A27: Total Equity | B27: ='08 Balance Sheet'!B34 -> 19.1 | C27: ='08 Balance Sheet'!C34 -> 28.8 | D27: ='08 Balance Sheet'!D34 -> 49 | E27: ='08 Balance Sheet'!E34 -> 79.3 | F27: ='08 Balance Sheet'!F34 -> 153.9 | G27: –
A28: Total Capital Employed | B28: ='08 Balance Sheet'!B22+'08 Balance Sheet'!B27+'08 Balance Sheet'!B34 -> 39.1 | C28: ='08 Balance Sheet'!C22+'08 Balance Sheet'!C27+'08 Balance Sheet'!C34 -> 46.7 | D28: ='08 Balance Sheet'!D22+'08 Balance Sheet'!D27+'08 Balance Sheet'!D34 -> 64.8 | E28: ='08 Balance Sheet'!E22+'08 Balance Sheet'!E27+'08 Balance Sheet'!E34 -> 89.8 | F28: ='08 Balance Sheet'!F22+'08 Balance Sheet'!F27+'08 Balance Sheet'!F34 -> 158.4 | G28: –
A29: CAPITAL WEIGHTS
A30: Weight of Debt (Wd) | B30: =('08 Balance Sheet'!B22+'08 Balance Sheet'!B27)/('08 Balance Sheet'!B22+'08 Balance Sheet'!B27+'08 Balance Sheet'!B34) -> 0.51150895 | C30: =('08 Balance Sheet'!C22+'08 Balance Sheet'!C27)/('08 Balance Sheet'!C22+'08 Balance Sheet'!C27+'08 Balance Sheet'!C34) -> 0.38329764 | D30: =('08 Balance Sheet'!D22+'08 Balance Sheet'!D27)/('08 Balance Sheet'!D22+'08 Balance Sheet'!D27+'08 Balance Sheet'!D34) -> 0.24382716 | E30: =('08 Balance Sheet'!E22+'08 Balance Sheet'!E27)/('08 Balance Sheet'!E22+'08 Balance Sheet'!E27+'08 Balance Sheet'!E34) -> 0.1169265 | F30: =('08 Balance Sheet'!F22+'08 Balance Sheet'!F27)/('08 Balance Sheet'!F22+'08 Balance Sheet'!F27+'08 Balance Sheet'!F34) -> 0.028409091 | G30: –
A31: Weight of Equity (We) | B31: ='08 Balance Sheet'!B34/('08 Balance Sheet'!B22+'08 Balance Sheet'!B27+'08 Balance Sheet'!B34) -> 0.48849105 | C31: ='08 Balance Sheet'!C34/('08 Balance Sheet'!C22+'08 Balance Sheet'!C27+'08 Balance Sheet'!C34) -> 0.61670236 | D31: ='08 Balance Sheet'!D34/('08 Balance Sheet'!D22+'08 Balance Sheet'!D27+'08 Balance Sheet'!D34) -> 0.75617284 | E31: ='08 Balance Sheet'!E34/('08 Balance Sheet'!E22+'08 Balance Sheet'!E27+'08 Balance Sheet'!E34) -> 0.8830735 | F31: ='08 Balance Sheet'!F34/('08 Balance Sheet'!F22+'08 Balance Sheet'!F27+'08 Balance Sheet'!F34) -> 0.97159091 | G31: –
A32: COST OF CAPITAL
A33: Cost of Equity — Ke (CAPM) | B33: ='04 Assumptions'!B38+'04 Assumptions'!B40*'04 Assumptions'!B39 -> 0.16075 | C33: ='04 Assumptions'!B38+'04 Assumptions'!B40*'04 Assumptions'!B39 -> 0.16075 | D33: ='04 Assumptions'!B38+'04 Assumptions'!B40*'04 Assumptions'!B39 -> 0.16075 | E33: ='04 Assumptions'!B38+'04 Assumptions'!B40*'04 Assumptions'!B39 -> 0.16075 | F33: ='04 Assumptions'!B38+'04 Assumptions'!B40*'04 Assumptions'!B39 -> 0.16075 | G33: ~20%
A34: Cost of Debt — Kd (Pre-Tax) | B34: ='04 Assumptions'!B41 -> 0.12 | C34: ='04 Assumptions'!B41 -> 0.12 | D34: ='04 Assumptions'!B41 -> 0.12 | E34: ='04 Assumptions'!B41 -> 0.12 | F34: ='04 Assumptions'!B41 -> 0.12 | G34: 12.0%
A35: After-Tax Cost of Debt Kd(1–T) | B35: ='04 Assumptions'!B41*(1-'04 Assumptions'!B34) -> 0.09 | C35: ='04 Assumptions'!B41*(1-'04 Assumptions'!B34) -> 0.09 | D35: ='04 Assumptions'!B41*(1-'04 Assumptions'!B34) -> 0.09 | E35: ='04 Assumptions'!B41*(1-'04 Assumptions'!B34) -> 0.09 | F35: ='04 Assumptions'!B41*(1-'04 Assumptions'!B34) -> 0.09 | G35: –
A36: WACC (Weighted Average) | B36: ='06 Financing'!G19 -> 0.17585455 | C36: ='06 Financing'!G19 -> 0.17585455 | D36: ='06 Financing'!G19 -> 0.17585455 | E36: ='06 Financing'!G19 -> 0.17585455 | F36: ='06 Financing'!G19 -> 0.17585455 | G36: ~14–16%
A37: LEVERAGE RATIOS
A38: Debt-to-Equity Ratio (D/E) | B38: =('08 Balance Sheet'!B22+'08 Balance Sheet'!B27)/'08 Balance Sheet'!B34 -> 1.0471204 | C38: =('08 Balance Sheet'!C22+'08 Balance Sheet'!C27)/'08 Balance Sheet'!C34 -> 0.62152778 | D38: =('08 Balance Sheet'!D22+'08 Balance Sheet'!D27)/'08 Balance Sheet'!D34 -> 0.32244898 | E38: =('08 Balance Sheet'!E22+'08 Balance Sheet'!E27)/'08 Balance Sheet'!E34 -> 0.13240858 | F38: =('08 Balance Sheet'!F22+'08 Balance Sheet'!F27)/'08 Balance Sheet'!F34 -> 0.029239766 | G38: < 1.0x
A39: Interest Coverage (EBIT/Interest) | B39: =IF('07 P&L'!B30>0,'07 P&L'!B29/'07 P&L'!B30,"N/A") -> 4789.9739 | C39: =IF('07 P&L'!C30>0,'07 P&L'!C29/'07 P&L'!C30,"N/A") -> 12950.978 | D39: =IF('07 P&L'!D30>0,'07 P&L'!D29/'07 P&L'!D30,"N/A") -> 32866.109 | E39: =IF('07 P&L'!E30>0,'07 P&L'!E29/'07 P&L'!E30,"N/A") -> 70229.32 | F39: =IF('07 P&L'!F30>0,'07 P&L'!F29/'07 P&L'!F30,"N/A") -> 165669.4 | G39: > 2.0x
A40: Net Debt / EBITDA | B40: =IF('07 P&L'!B27>0,('08 Balance Sheet'!B22+'08 Balance Sheet'!B27-'08 Balance Sheet'!B5)/'07 P&L'!B27,"N/A") -> 0.00068032518 | C40: =IF('07 P&L'!C27>0,('08 Balance Sheet'!C22+'08 Balance Sheet'!C27-'08 Balance Sheet'!C5)/'07 P&L'!C27,"N/A") -> -1.3424688e-05 | D40: =IF('07 P&L'!D27>0,('08 Balance Sheet'!D22+'08 Balance Sheet'!D27-'08 Balance Sheet'!D5)/'07 P&L'!D27,"N/A") -> -0.00020575331 | E40: =IF('07 P&L'!E27>0,('08 Balance Sheet'!E22+'08 Balance Sheet'!E27-'08 Balance Sheet'!E5)/'07 P&L'!E27,"N/A") -> -0.00031493638 | F40: =IF('07 P&L'!F27>0,('08 Balance Sheet'!F22+'08 Balance Sheet'!F27-'08 Balance Sheet'!F5)/'07 P&L'!F27,"N/A") -> -0.00036827263 | G40: < 3.0x
A41: Note: Total Debt = Short-term OD + SIDBI Term Loan. Net Debt = Total Debt – Cash & Bank. Ke via CAPM; Kd from 04 Assumptions. All values derived from 04 Assumptions, 07 P&L and 08 Balance Sheet.

Sheet 07 P&L
A1: PROJECTED INCOME STATEMENT (₹ Lakhs) | FY2026 – FY2030
A2: Line Item | B2: FY2026 (Y1) | C2: FY2027 (Y2) | D2: FY2028 (Y3) | E2: FY2029 (Y4) | F2: FY2030 (Y5)
A3: REVENUE
A4: B2C Units | B4: 500 | C4: 1200 | D4: 2500 | E4: 4200 | F4: 6800
A5: B2B Units | B5: 200 | C5: 600 | D5: 1400 | E5: 2600 | F5: 4200
A6: B2C ASP (₹) | B6: 3999 | C6: 4119 | D6: 4242 | E6: 4454 | F6: 4677
A7: B2B ASP (₹) | B7: 3499 | C7: 3569 | D7: 3640 | E7: 3749 | F7: 3862
A8: B2C Revenue | B8: =B4*B6/100 -> 19995 | C8: =C4*C6/100 -> 49428 | D8: =D4*D6/100 -> 106050 | E8: =E4*E6/100 -> 187068 | F8: =F4*F6/100 -> 318036
A9: B2B Revenue | B9: =B5*B7/100 -> 6998 | C9: =C5*C7/100 -> 21414 | D9: =D5*D7/100 -> 50960 | E9: =E5*E7/100 -> 97474 | F9: =F5*F7/100 -> 162204
A10: Subscription Revenue | B10: 0 | C10: 3.99 | D10: 11.18 | E10: 25.57 | F10: 51.13
A11: GROSS REVENUE | B11: =SUM(B8:B10) -> 26993 | C11: =SUM(C8:C10) -> 70845.99 | D11: =SUM(D8:D10) -> 157021.18 | E11: =SUM(E8:E10) -> 284567.57 | F11: =SUM(F8:F10) -> 480291.13
A12: COST OF GOODS SOLD
A13: Material Cost | B13: =(B4+B5)*18 -> 12600 | C13: =(C4+C5)*18 -> 32400 | D13: =(D4+D5)*18 -> 70200 | E13: =(E4+E5)*18 -> 122400 | F13: =(F4+F5)*18 -> 198000
A14: Labour Cost | B14: =(B4+B5)*2.2 -> 1540 | C14: =(C4+C5)*2.2 -> 3960 | D14: =(D4+D5)*2.2 -> 8580 | E14: =(E4+E5)*2.2 -> 14960 | F14: =(F4+F5)*2.2 -> 24200
A15: Logistics Cost | B15: =(B4+B5)*1.8 -> 1260 | C15: =(C4+C5)*1.8 -> 3240 | D15: =(D4+D5)*1.8 -> 7020 | E15: =(E4+E5)*1.8 -> 12240 | F15: =(F4+F5)*1.8 -> 19800
A16: Warranty Provision | B16: =B11*0.02 -> 539.86 | C16: =C11*0.02 -> 1416.9198 | D16: =D11*0.02 -> 3140.4236 | E16: =E11*0.02 -> 5691.3514 | F16: =F11*0.02 -> 9605.8226
A17: TOTAL COGS | B17: =SUM(B13:B16) -> 15939.86 | C17: =SUM(C13:C16) -> 41016.92 | D17: =SUM(D13:D16) -> 88940.424 | E17: =SUM(E13:E16) -> 155291.35 | F17: =SUM(F13:F16) -> 251605.82
A18: GROSS PROFIT | B18: =B11-B17 -> 11053.14 | C18: =C11-C17 -> 29829.07 | D18: =D11-D17 -> 68080.756 | E18: =E11-E17 -> 129276.22 | F18: =F11-F17 -> 228685.31
A19: Gross Margin % | B19: =B18/B11 -> 0.40948172 | C19: =C18/C11 -> 0.42104105 | D19: =D18/D11 -> 0.4335769 | E19: =E18/E11 -> 0.45429006 | F19: =F18/F11 -> 0.47613894
A20: OPERATING EXPENSES
A21: Salaries & Benefits | B21: 12 | C21: 13.8 | D21: 15.87 | E21: 18.25 | F21: 20.99
A22: Marketing & Brand | B22: 8 | C22: 9.6 | D22: 11.52 | E22: 13.82 | F22: 16.59
A23: R&D / Product Development | B23: 5 | C23: 5.5 | D23: 6.05 | E23: 6.66 | F23: 7.32
A24: G&A / Overheads | B24: 4 | C24: 4.32 | D24: 4.67 | E24: 5.04 | F24: 5.44
A25: Depreciation & Amortisation | B25: 7.2 | C25: 8.6 | D25: 9.8 | E25: 10.5 | F25: 11.2
A26: TOTAL OPEX | B26: =SUM(B21:B25) -> 36.2 | C26: =SUM(C21:C25) -> 41.82 | D26: =SUM(D21:D25) -> 47.91 | E26: =SUM(E21:E25) -> 54.27 | F26: =SUM(F21:F25) -> 61.54
A27: EBITDA | B27: =B18-B26+B25 -> 11024.14 | C27: =C18-C26+C25 -> 29795.85 | D27: =D18-D26+D25 -> 68042.646 | E27: =E18-E26+E25 -> 129232.45 | F27: =F18-F26+F25 -> 228634.97
A28: EBITDA Margin % | B28: =IF(B11>0,B27/B11,0) -> 0.40840736 | C28: =IF(C11>0,C27/C11,0) -> 0.42057215 | D28: =IF(D11>0,D27/D11,0) -> 0.43333419 | E28: =IF(E11>0,E27/E11,0) -> 0.45413625 | F28: =IF(F11>0,F27/F11,0) -> 0.47603412
A29: EBIT (Operating Profit) | B29: =B18-B26 -> 11016.94 | C29: =C18-C26 -> 29787.25 | D29: =D18-D26 -> 68032.846 | E29: =E18-E26 -> 129221.95 | F29: =F18-F26 -> 228623.77
A30: Interest Expense | B30: 2.3 | C30: 2.3 | D30: 2.07 | E30: 1.84 | F30: 1.38
A31: EBT (Profit Before Tax) | B31: =B29-B30 -> 11014.64 | C31: =C29-C30 -> 29784.95 | D31: =D29-D30 -> 68030.776 | E31: =E29-E30 -> 129220.11 | F31: =F29-F30 -> 228622.39
A32: Tax (25%) | B32: =IF(B31>0,B31*0.25,0) -> 2753.66 | C32: =IF(C31>0,C31*0.25,0) -> 7446.2376 | D32: =IF(D31>0,D31*0.25,0) -> 17007.694 | E32: =IF(E31>0,E31*0.25,0) -> 32305.027 | F32: =IF(F31>0,F31*0.25,0) -> 57155.597
A33: NET PROFIT AFTER TAX (PAT) | B33: =B31-B32 -> 8260.98 | C33: =C31-C32 -> 22338.713 | D33: =D31-D32 -> 51023.082 | E33: =E31-E32 -> 96915.081 | F33: =F31-F32 -> 171466.79
A34: PAT Margin % | B34: =IF(B11>0,B33/B11,0) -> 0.30604157 | C34: =IF(C11>0,C33/C11,0) -> 0.31531372 | D34: =IF(D11>0,D33/D11,0) -> 0.32494395 | E34: =IF(E11>0,E33/E11,0) -> 0.34056966 | F34: =IF(F11>0,F33/F11,0) -> 0.35700595

Sheet 08 Balance Sheet
A1: PROJECTED BALANCE SHEET (₹ Lakhs) | FY2026 – FY2030
B2: FY2026 (Y1) | C2: FY2027 (Y2) | D2: FY2028 (Y3) | E2: FY2029 (Y4) | F2: FY2030 (Y5)
A3: ASSETS
A4: Current Assets
A5: Cash & Bank | B5: 12.5 | C5: 18.3 | D5: 29.8 | E5: 51.2 | F5: 88.7
A6: Accounts Receivable | B6: 3.5 | C6: 7.2 | D6: 13.8 | E6: 22.5 | F6: 36.2
A7: Inventory | B7: 11 | C7: 13.2 | D7: 16.5 | E7: 20.8 | F7: 26.4
A8: Prepaid & Other CA | B8: 1.5 | C8: 2 | D8: 2.5 | E8: 3 | F8: 3.5
A9: TOTAL CURRENT ASSETS | B9: =SUM(B5:B8) -> 28.5 | C9: =SUM(C5:C8) -> 40.7 | D9: =SUM(D5:D8) -> 62.6 | E9: =SUM(E5:E8) -> 97.5 | F9: =SUM(F5:F8) -> 154.8
A10: Non-Current Assets
A11: Plant, Property & Equipment (Gross) | B11: 12 | C11: 18 | D11: 28 | E11: 36 | F11: 71
A12: Less: Accumulated Depreciation | B12: -2.4 | C12: -5.4 | D12: -9.4 | E12: -14.4 | F12: -20.7
A13: Net PPE | B13: =B11+B12 -> 9.6 | C13: =C11+C12 -> 12.6 | D13: =D11+D12 -> 18.6 | E13: =E11+E12 -> 21.6 | F13: =F11+F12 -> 50.3
A14: Intangible Assets (net) | B14: 8.2 | C14: 5.8 | D14: 3.4 | E14: 2 | F14: 0.8
A15: Security Deposits | B15: 0.5 | C15: 0.5 | D15: 0.5 | E15: 0.5 | F15: 0.5
A16: TOTAL NON-CURRENT ASSETS | B16: =SUM(B13:B15) -> 18.3 | C16: =SUM(C13:C15) -> 18.9 | D16: =SUM(D13:D15) -> 22.5 | E16: =SUM(E13:E15) -> 24.1 | F16: =SUM(F13:F15) -> 51.6
A17: TOTAL ASSETS | B17: =B9+B16 -> 46.8 | C17: =C9+C16 -> 59.6 | D17: =D9+D16 -> 85.1 | E17: =E9+E16 -> 121.6 | F17: =F9+F16 -> 206.4
A19: LIABILITIES & EQUITY
A20: Current Liabilities
A21: Accounts Payable | B21: 4.5 | C21: 7.2 | D21: 11.5 | E21: 17.8 | F21: 26.5
A22: Short-term Debt / OD | B22: 5 | C22: 5 | D22: 5 | E22: 3 | F22: 0
A23: GST & Tax Payables | B23: 1.2 | C23: 2.5 | D23: 4.2 | E23: 7.5 | F23: 12.8
A24: Accrued Expenses | B24: 1.5 | C24: 2 | D24: 2.5 | E24: 3 | F24: 3.5
A25: TOTAL CURRENT LIABILITIES | B25: =SUM(B21:B24) -> 12.2 | C25: =SUM(C21:C24) -> 16.7 | D25: =SUM(D21:D24) -> 23.2 | E25: =SUM(E21:E24) -> 31.3 | F25: =SUM(F21:F24) -> 42.8
A26: Non-Current Liabilities
A27: Term Loan (SIDBI) | B27: 15 | C27: 12.9 | D27: 10.8 | E27: 7.5 | F27: 4.5
A28: Deferred Tax Liability | B28: 0.5 | C28: 1.2 | D28: 2.1 | E28: 3.5 | F28: 5.2
A29: TOTAL NCL | B29: =SUM(B27:B28) -> 15.5 | C29: =SUM(C27:C28) -> 14.1 | D29: =SUM(D27:D28) -> 12.9 | E29: =SUM(E27:E28) -> 11 | F29: =SUM(F27:F28) -> 9.7
A30: EQUITY
A31: Share Capital | B31: 30 | C31: 30 | D31: 30 | E31: 30 | F31: 30
A32: Grants (Capital Reserve) | B32: 5 | C32: 5 | D32: 5 | E32: 5 | F32: 5
A33: Retained Earnings (c/f) | B33: =B17-B25-B29-B31-B32 -> -15.9 | C33: =C17-C25-C29-C31-C32 -> -6.2 | D33: =D17-D25-D29-D31-D32 -> 14 | E33: =E17-E25-E29-E31-E32 -> 44.3 | F33: =F17-F25-F29-F31-F32 -> 118.9
A34: TOTAL EQUITY | B34: =SUM(B31:B33) -> 19.1 | C34: =SUM(C31:C33) -> 28.8 | D34: =SUM(D31:D33) -> 49 | E34: =SUM(E31:E33) -> 79.3 | F34: =SUM(F31:F33) -> 153.9
A35: TOTAL LIABILITIES + EQUITY | B35: =B25+B29+B34 -> 46.8 | C35: =C25+C29+C34 -> 59.6 | D35: =D25+D29+D34 -> 85.1 | E35: =E25+E29+E34 -> 121.6 | F35: =F25+F29+F34 -> 206.4
A36: CHECK (Assets = Liab+Equity) | B36: =B17-B35 -> 0 | C36: =C17-C35 -> 0 | D36: =D17-D35 -> 0 | E36: =E17-E35 -> 0 | F36: =F17-F35 -> 0

Sheet 09 Cash Flow
A1: PROJECTED CASH FLOW STATEMENT (₹ Lakhs) | FY2026 – FY2030
B2: FY2026 (Y1) | C2: FY2027 (Y2) | D2: FY2028 (Y3) | E2: FY2029 (Y4) | F2: FY2030 (Y5)
A3: A. OPERATING ACTIVITIES
A4: Net Profit After Tax | B4: ='07 P&L'!B33 -> 8260.98 | C4: ='07 P&L'!C33 -> 22338.713 | D4: ='07 P&L'!D33 -> 51023.082 | E4: ='07 P&L'!E33 -> 96915.081 | F4: ='07 P&L'!F33 -> 171466.79
A5: Add: Depreciation & Amortisation | B5: 7.2 | C5: 8.6 | D5: 9.8 | E5: 10.5 | F5: 11.2
A6: Add: Interest Expense | B6: 2.3 | C6: 2.3 | D6: 2.07 | E6: 1.84 | F6: 1.38
A7: Changes in Working Capital
A8: (Increase)/Decrease in Receivables | B8: -3.5 | C8: -3.7 | D8: -6.6 | E8: -8.7 | F8: -13.7
A9: (Increase)/Decrease in Inventory | B9: -11 | C9: -2.2 | D9: -3.3 | E9: -4.3 | F9: -5.6
A10: Increase/(Decrease) in Payables | B10: 4.5 | C10: 2.7 | D10: 4.3 | E10: 6.3 | F10: 8.7
A11: Other working capital changes | B11: 0.8 | C11: 1 | D11: 1.2 | E11: 1.5 | F11: 1.8
A12: NET CASH FROM OPERATIONS | B12: =SUM(B4:B11) -> 8261.28 | C12: =SUM(C4:C11) -> 22347.413 | D12: =SUM(D4:D11) -> 51030.552 | E12: =SUM(E4:E11) -> 96922.221 | F12: =SUM(F4:F11) -> 171470.57
A13: B. INVESTING ACTIVITIES
A14: Purchase of PPE | B14: -12 | C14: -6 | D14: -10 | E14: -8 | F14: -35
A15: Intangible Asset Investments | B15: -9 | C15: 0 | D15: -1.5 | E15: -1 | F15: 0
A16: Security Deposits | B16: -0.5 | C16: 0 | D16: 0 | E16: 0 | F16: 0
A17: NET CASH FROM INVESTING | B17: =SUM(B14:B16) -> -21.5 | C17: =SUM(C14:C16) -> -6 | D17: =SUM(D14:D16) -> -11.5 | E17: =SUM(E14:E16) -> -9 | F17: =SUM(F14:F16) -> -35
A18: C. FINANCING ACTIVITIES
A19: Equity Raised | B19: 30 | C19: 0 | D19: 0 | E19: 0 | F19: 0
A20: Grant Received | B20: 5 | C20: 0 | D20: 0 | E20: 0 | F20: 0
A21: Term Loan Drawdown | B21: 15 | C21: 0 | D21: 0 | E21: 0 | F21: 0
A22: Loan Repayments | B22: 0 | C22: -2.1 | D22: -2.1 | E22: -3.3 | F22: -3
A23: Interest Paid | B23: -2.3 | C23: -2.3 | D23: -2.07 | E23: -1.84 | F23: -1.38
A24: Dividends Paid | B24: 0 | C24: 0 | D24: 0 | E24: 0 | F24: 0
A25: NET CASH FROM FINANCING | B25: =SUM(B19:B24) -> 47.7 | C25: =SUM(C19:C24) -> -4.4 | D25: =SUM(D19:D24) -> -4.17 | E25: =SUM(E19:E24) -> -5.14 | F25: =SUM(F19:F24) -> -4.38
A26: NET CHANGE IN CASH | B26: =B12+B17+B25 -> 8287.48 | C26: =C12+C17+C25 -> 22337.013 | D26: =D12+D17+D25 -> 51014.882 | E26: =E12+E17+E25 -> 96908.081 | F26: =F12+F17+F25 -> 171431.19
A27: Opening Cash Balance | B27: 0 | C27: =B5 -> 7.2 | D27: =C5 -> 8.6 | E27: =D5 -> 9.8 | F27: =E5 -> 10.5
A28: CLOSING CASH BALANCE | B28: =B27+B26 -> 8287.48 | C28: =C27+C26 -> 22344.213 | D28: =D27+D26 -> 51023.482 | E28: =E27+E26 -> 96917.881 | F28: =F27+F26 -> 171441.69

Sheet 10 Cap Budget
A1: CAPITAL BUDGETING & PROJECT EVALUATION
A3: 10.1 FREE CASH FLOW TO FIRM (FCFF) (₹ Lakhs)
A4: Component | B4: FY2026 (Y1) | C4: FY2027 (Y2) | D4: FY2028 (Y3) | E4: FY2029 (Y4) | F4: FY2030 (Y5)
A5: EBIT | B5: ='07 P&L'!B29 -> 11016.94 | C5: ='07 P&L'!C29 -> 29787.25 | D5: ='07 P&L'!D29 -> 68032.846 | E5: ='07 P&L'!E29 -> 129221.95 | F5: ='07 P&L'!F29 -> 228623.77
A6: Less: Tax on EBIT | B6: =B5*0.25 -> 2754.235 | C6: =C5*0.25 -> 7446.8126 | D6: =D5*0.25 -> 17008.212 | E6: =E5*0.25 -> 32305.487 | F6: =F5*0.25 -> 57155.942
A7: NOPAT | B7: =B5-B6 -> 8262.705 | C7: =C5-C6 -> 22340.438 | D7: =D5-D6 -> 51024.635 | E7: =E5-E6 -> 96916.461 | F7: =F5-F6 -> 171467.83
A8: Add: D&A | B8: 7.2 | C8: 8.6 | D8: 9.8 | E8: 10.5 | F8: 11.2
A9: Less: CapEx | B9: -12 | C9: -6 | D9: -10 | E9: -8 | F9: -35
A10: Less: ΔNWC | B10: -9.2 | C10: -2.2 | D10: -4.4 | E10: -5.2 | F10: -8.8
A11: FCFF | B11: =B7+B8+B9+B10 -> 8248.705 | C11: =C7+C8+C9+C10 -> 22340.838 | D11: =D7+D8+D9+D10 -> 51020.035 | E11: =E7+E8+E9+E10 -> 96913.761 | F11: =F7+F8+F9+F10 -> 171435.23
A13: 10.2 DCF VALUATION (₹ Lakhs)
A14: WACC (discount rate) | B14: ='06 Financing'!G19 -> 0.17585455
A15: Terminal Growth Rate | B15: ='04 Assumptions'!B38 -> 0.073
A16: Terminal Value (Gordon Growth) | B16: =F11*(1+B15)/(B14-B15) -> 1788447.9
A17: DCF Component | B17: FY2026 (Y1) | C17: FY2027 (Y2) | D17: FY2028 (Y3) | E17: FY2029 (Y4) | F17: FY2030 (Y5)
A18: Year | B18: 1 | C18: 2 | D18: 3 | E18: 4 | F18: 5
A19: FCFF | B19: =B11 -> 8248.705 | C19: =C11 -> 22340.838 | D19: =D11 -> 51020.035 | E19: =E11 -> 96913.761 | F19: =F11 -> 171435.23
A20: Add: Terminal Value (Year 5 only) | B20: 0 | C20: 0 | D20: 0 | E20: 0 | F20: =$B$16 -> 1788447.9
A21: Total Cash Flow | B21: =B19+B20 -> 8248.705 | C21: =C19+C20 -> 22340.838 | D21: =D19+D20 -> 51020.035 | E21: =E19+E20 -> 96913.761 | F21: =F19+F20 -> 1959883.1
A22: Discount Factor | B22: =1/(1+$B$14)^B18 -> 0.85044532 | C22: =1/(1+$B$14)^C18 -> 0.72325725 | D22: =1/(1+$B$14)^D18 -> 0.61509075 | E22: =1/(1+$B$14)^E18 -> 0.52310105 | F22: =1/(1+$B$14)^F18 -> 0.44486884
A23: PV of Cash Flow | B23: =B21*B22 -> 7015.0726 | C23: =C21*C22 -> 16158.173 | D23: =D21*D22 -> 31381.951 | E23: =E21*E22 -> 50695.69 | F23: =F21*F22 -> 871890.94
A24: SUM OF PV (Enterprise Value) | B24: =SUM(B23:F23) -> 977141.83
A26: 10.3 PROJECT EVALUATION METRICS
A27: Initial Investment (₹L) | B27: 55
A28: NPV (₹ Lakhs) | B28: =B24-B27 -> 977086.83
A29: IRR (Project Cash Flows Y0–Y5) | B29: N/A
A30: Payback Period (Years) | B30: 3.2
A31: Profitability Index (NPV+Investment)/Investment | B31: =(B28+B27)/B27 -> 17766.215
A33: 10.4 NPV SENSITIVITY (₹L) – WACC vs Terminal Growth Rate
A34: WACC → / TGR ↓ | B34: 10% | C34: 12% | D34: 14% | E34: 16% | F34: 18% | G34: 20%
A35: TGR 2% | B35: 201.4 | C35: 139 | D35: 98.1 | E35: 69.4 | F35: 48.2 | G35: 32.1
A36: TGR 3% | B36: 235.5 | C36: 158.8 | D36: 110.7 | E36: 77.9 | F36: 54.2 | G36: 36.5
A37: TGR 4% | B37: 281.1 | C37: 183.5 | D37: 125.7 | E37: 87.8 | F37: 61.1 | G37: 41.4
A38: TGR 5% | B38: 344.8 | C38: 215.3 | D38: 144.1 | E38: 99.5 | F38: 69 | G38: 47.1
A39: TGR 6% | B39: 440.4 | C39: 257.7 | D39: 167.2 | E39: 113.5 | F39: 78.3 | G39: 53.5

Sheet 11 Conclusion
A1: CONCLUSION & INVESTMENT HIGHLIGHTS
A3: 11.1 KEY FINANCIAL KPIs SUMMARY
A4: KPI | B4: FY1 | C4: FY2 | D4: FY3 | E4: FY4 | F4: FY5 | G4: Benchmark
A5: Revenue (₹ Lakhs) | B5: ='07 P&L'!B11 -> 26993 | C5: ='07 P&L'!C11 -> 70845.99 | D5: ='07 P&L'!D11 -> 157021.18 | E5: ='07 P&L'!E11 -> 284567.57 | F5: ='07 P&L'!F11 -> 480291.13 | G5: Growing >28% CAGR
A6: Gross Margin % | B6: ='07 P&L'!B19 -> 0.40948172 | C6: ='07 P&L'!C19 -> 0.42104105 | D6: ='07 P&L'!D19 -> 0.4335769 | E6: ='07 P&L'!E19 -> 0.45429006 | F6: ='07 P&L'!F19 -> 0.47613894 | G6: >45% (Y3+)
A7: EBITDA (₹ Lakhs) | B7: ='07 P&L'!B27 -> 11024.14 | C7: ='07 P&L'!C27 -> 29795.85 | D7: ='07 P&L'!D27 -> 68042.646 | E7: ='07 P&L'!E27 -> 129232.45 | F7: ='07 P&L'!F27 -> 228634.97 | G7: Positive from Y2
A8: EBITDA Margin % | B8: ='07 P&L'!B28 -> 0.40840736 | C8: ='07 P&L'!C28 -> 0.42057215 | D8: ='07 P&L'!D28 -> 0.43333419 | E8: ='07 P&L'!E28 -> 0.45413625 | F8: ='07 P&L'!F28 -> 0.47603412 | G8: >15% (Y3+)
A9: PAT (₹ Lakhs) | B9: ='07 P&L'!B33 -> 8260.98 | C9: ='07 P&L'!C33 -> 22338.713 | D9: ='07 P&L'!D33 -> 51023.082 | E9: ='07 P&L'!E33 -> 96915.081 | F9: ='07 P&L'!F33 -> 171466.79 | G9: Positive Y2+
A10: PAT Margin % | B10: ='07 P&L'!B34 -> 0.30604157 | C10: ='07 P&L'!C34 -> 0.31531372 | D10: ='07 P&L'!D34 -> 0.32494395 | E10: ='07 P&L'!E34 -> 0.34056966 | F10: ='07 P&L'!F34 -> 0.35700595 | G10: >10% (Y4+)
A11: Cash Balance (₹L) | B11: ='09 Cash Flow'!B28 -> 8287.48 | C11: ='09 Cash Flow'!C28 -> 22344.213 | D11: ='09 Cash Flow'!D28 -> 51023.482 | E11: ='09 Cash Flow'!E28 -> 96917.881 | F11: ='09 Cash Flow'!F28 -> 171441.69 | G11: Always positive
A12: Total Units Sold | B12: ='07 P&L'!B4+'07 P&L'!B5 -> 700 | C12: ='07 P&L'!C4+'07 P&L'!C5 -> 1800 | D12: ='07 P&L'!D4+'07 P&L'!D5 -> 3900 | E12: ='07 P&L'!E4+'07 P&L'!E5 -> 6800 | F12: ='07 P&L'!F4+'07 P&L'!F5 -> 11000 | G12: 11,000 by Y5
A13: NPV (₹ Lakhs) | B13: ='10 Cap Budget'!B28 -> 977086.83 | G13: Must be > 0
A14: IRR | B14: ='10 Cap Budget'!B29 -> N/A | G14: >WACC (target >20%)
A15: Payback Period (Years) | B15: ='10 Cap Budget'!B30 -> 3.2 | G15: < 4 Years
A16: WACC | B16: ='06 Financing'!G19 -> 0.17585455 | G16: ~14–16%
A18: 11.2 INVESTMENT HIGHLIGHTS
A19: Large & Fast-Growing Market | B19: India's EV 2-wheeler market grows at ~28% CAGR; apartment housing is the fastest-growing urban segment.
A20: Clear Product-Market Fit | B20: No foldable, apartment-specific smart dock exists — ScootCharge fills a genuine white-space gap.
A21: Lean Capital Model | B21: Total CapEx of ~₹55L is modest; break-even achieved at ~1,700 units — easily within Year 2 targets.
A22: Multiple Revenue Streams | B22: Hardware (B2C + B2B) + recurring SaaS subscription creates a diversified, scalable revenue model.
A23: Strong Financial Returns | B23: DCF-based NPV strongly positive; IRR expected to exceed WACC by 10–15% at base-case projections.
A24: Regulatory Tailwind | B24: FAME-II policy, DPIIT startup grants, and mandatory EV-ready building codes reduce risk & cost.
A25: Scalable B2B Channel | B25: Housing society bulk deals (10–200 units) provide high-volume, low-CAC revenue with recurring service contracts.
A26: Experienced Team | B26: 4-founder team with complementary skills in hardware engineering, software, finance, and sales.
A29: CONCLUSION: ScootCharge Solutions Pvt. Ltd. presents a compelling investment opportunity at the intersection of India's EV revolution and urban apartment growth. With a clearly differentiated product, a lean capital structure, strong government policy support, and a credible path to profitability by Year 2, the business is well-positioned to capture significant market share in an under-served, high-growth segment. The financial projections demonstrate robust NPV, an IRR exceeding WACC, and a payback period of approximately 3.2 years — making this a financially sound and strategically compelling start-up venture.
